MANIFEST.in
setup.py
umapi_client/__init__.py
umapi_client/client.py
umapi_client/config.py
wmf_umapi_client.egg-info/PKG-INFO
wmf_umapi_client.egg-info/SOURCES.txt
wmf_umapi_client.egg-info/dependency_links.txt
wmf_umapi_client.egg-info/requires.txt
wmf_umapi_client.egg-info/top_level.txt