Metadata-Version: 1.0
Name: wmf-umapi-client
Version: 0.1.1-dev
Summary: Client wrapper for Wikimedia UMAPI.
Home-page: http://www.github.com/rfaulkner/umapi_client
Author: Wikimedia Foundation
Author-email: e3-team@lists.wikimedia.org
License: UNKNOWN
Platform: UNKNOWN
Classifier: Development Status :: 4 - Beta
Classifier: Intended Audience :: Science/Research
Classifier: License :: OSI Approved :: GNU General Public License (GPL)
Classifier: Programming Language :: Python :: 2.7
Classifier: Programming Language :: Python
Classifier: Topic :: Scientific/Engineering :: Information Analysis
Classifier: Topic :: Software Development :: Libraries :: Python Modules
